cmd2_submenu/__init__.py
cmd2_submenu/submenu.py
cmd2_submenu-0.3.0.dist-info/METADATA
cmd2_submenu-0.3.0.dist-info/RECORD
cmd2_submenu-0.3.0.dist-info/WHEEL
cmd2_submenu-0.3.0.dist-info/top_level.txt
