Metadata-Version: 2.1
Name: cmd2-submenu
Version: 0.3.0
Summary: A nested submenu system for cmd2
Home-page: https://github.com/python-cmd2/cmd2-submenu
Author: python-cmd2
Author-email: 
License: MIT
Keywords: cmd2 plugin submenu
Platform: UNKNOWN
Classifier: Development Status :: 4 - Beta
Classifier: Environment :: Console
Classifier: Operating System :: OS Independent
Classifier: Topic :: Software Development :: Libraries :: Python Modules
Classifier: Intended Audience :: Developers
Classifier: License :: OSI Approved :: MIT License
Classifier: Programming Language :: Python :: 3.4
Classifier: Programming Language :: Python :: 3.5
Classifier: Programming Language :: Python :: 3.6
Classifier: Programming Language :: Python :: 3.7
Requires-Python: >=3.4
Provides-Extra: dev
Requires-Dist: cmd2 (<=2,>=0.9.6)
Provides-Extra: dev
Requires-Dist: setuptools-scm; extra == 'dev'
Requires-Dist: pytest; extra == 'dev'
Requires-Dist: invoke; extra == 'dev'
